{
  "audiovisual_files": {
    "30d7d1bc-a8e4-44fb-befc-ec4a4626a762": {
      "label": "Rita Moreno",
      "is_offline": false,
      "file_type": "Audio",
      "file_url": "https://drive.google.com/file/d/1o2fmEY96Z1lcKGI8aX1YjFlh32gwschi/view?usp=drive_link",
      "duration": 330
    }
  },
  "auto_generate_web_page": true,
  "label": "Rita Moreno - Latino USA Episode 411",
  "created_at": "2025-10-27T19:43:52.633Z",
  "created_by": "amtellez16",
  "updated_at": "2025-10-27T19:43:52.633Z",
  "updated_by": "amtellez16"
}